basestation/__init__.py
basestation/const.py
basestation/device.py
basestation/scanner.py
basestation-0.0.4.dist-info/AUTHORS.rst
basestation-0.0.4.dist-info/LICENSE.txt
basestation-0.0.4.dist-info/METADATA
basestation-0.0.4.dist-info/WHEEL
basestation-0.0.4.dist-info/top_level.txt
basestation-0.0.4.dist-info/RECORD
