Metadata-Version: 2.1
Name: basestation
Version: 0.0.4
Summary: A library to read/write power states from Valve Index® Base Stations through BLE
Home-page: https://github.com/jariz/basestation
Author: Jari Zwarts
Author-email: jarizw@gmail.com
License: MIT
Project-URL: Twitter, https://twitter.com/JariZwarts
Platform: any
Classifier: Development Status :: 4 - Beta
Classifier: Programming Language :: Python
Requires-Dist: bluepy (<2.0,>=1.3)
Provides-Extra: testing
Requires-Dist: setuptools ; extra == 'testing'
Requires-Dist: pytest ; extra == 'testing'
Requires-Dist: pytest-cov ; extra == 'testing'
